firelens/__init__.py
firelens/__main__.py
firelens/app.py
firelens/cert_manager.py
firelens/cli.py
firelens/collectors.py
firelens/config.py
firelens/database.py
firelens/interface_monitor.py
firelens/resources.py
firelens/saml_auth.py
firelens/ssl_manager.py
firelens/static/css/admin.css
firelens/static/css/styles.css
firelens/static/img/firelens-transparent-logo-darkmode.png
firelens/static/img/firelens-transparent-logo.png
firelens/static/js/admin-certificates.js
firelens/static/js/admin-dashboard.js
firelens/static/js/admin-firewall-form.js
firelens/static/js/admin-password.js
firelens/static/js/admin-saml.js
firelens/static/js/admin-ssl.js
firelens/static/js/admin-theme.js
firelens/static/js/chart.min.js
firelens/static/js/chartjs-adapter-date-fns.bundle.min.js
firelens/static/js/firewall-detail.js
firelens/templates/admin_certificates.html
firelens/templates/admin_dashboard.html
firelens/templates/admin_firewall_form.html
firelens/templates/admin_login.html
firelens/templates/admin_password.html
firelens/templates/admin_saml.html
firelens/templates/admin_saml_error.html
firelens/templates/admin_ssl.html
firelens/templates/dashboard.html
firelens/templates/firewall_detail.html
firelens/vendors/__init__.py
firelens/vendors/base.py
firelens/vendors/cisco_firepower.py
firelens/vendors/fortinet.py
firelens/vendors/palo_alto.py
firelens/web_dashboard/__init__.py
firelens/web_dashboard/app.py
firelens/web_dashboard/cache.py
firelens/web_dashboard/helpers.py
firelens/web_dashboard/middleware.py
firelens/web_dashboard/session.py
firelens/web_dashboard/routes/__init__.py
firelens/web_dashboard/routes/admin.py
firelens/web_dashboard/routes/auth.py
firelens/web_dashboard/routes/certificates.py
firelens/web_dashboard/routes/dashboard.py
firelens/web_dashboard/routes/saml.py
firelens/web_dashboard/routes/ssl.py
firelens_monitor-1.0.40.dist-info/METADATA
firelens_monitor-1.0.40.dist-info/WHEEL
firelens_monitor-1.0.40.dist-info/entry_points.txt
firelens_monitor-1.0.40.dist-info/licenses/LICENSE
firelens_monitor-1.0.40.dist-info/RECORD
