Metadata-Version: 2.4
Name: firelens-monitor
Version: 1.0.40
Summary: Multi-vendor firewall monitoring solution with real-time metrics collection
Project-URL: Homepage, https://github.com/mancow2001/FireLens
Project-URL: Documentation, https://github.com/mancow2001/FireLens#readme
Project-URL: Repository, https://github.com/mancow2001/FireLens
Project-URL: Issues, https://github.com/mancow2001/FireLens/issues
Author: FireLens Team
License: MIT License
License-File: LICENSE
Keywords: cisco,dashboard,firewall,fortinet,metrics,monitoring,network,palo-alto,security
Classifier: Development Status :: 4 - Beta
Classifier: Environment :: Console
Classifier: Environment :: Web Environment
Classifier: Framework :: FastAPI
Classifier: Intended Audience :: Information Technology
Classifier: Intended Audience :: System Administrators
Classifier: License :: OSI Approved :: MIT License
Classifier: Operating System :: OS Independent
Classifier: Programming Language :: Python :: 3
Classifier: Programming Language :: Python :: 3.9
Classifier: Programming Language :: Python :: 3.10
Classifier: Programming Language :: Python :: 3.11
Classifier: Programming Language :: Python :: 3.12
Classifier: Programming Language :: Python :: 3.13
Classifier: Topic :: System :: Monitoring
Classifier: Topic :: System :: Networking :: Monitoring
Requires-Python: >=3.9
Requires-Dist: bcrypt>=4.0.0
Requires-Dist: cryptography>=3.4.0
Requires-Dist: defusedxml>=0.7.0
Requires-Dist: fastapi>=0.68.0
Requires-Dist: jinja2>=3.0.0
Requires-Dist: psutil>=5.8.0
Requires-Dist: python-dotenv>=0.19.0
Requires-Dist: python-multipart>=0.0.5
Requires-Dist: python3-saml>=1.16.0
Requires-Dist: pyyaml>=6.0
Requires-Dist: requests>=2.25.0
Requires-Dist: slowapi>=0.1.9
Requires-Dist: uvicorn[standard]>=0.15.0
Provides-Extra: dev
Requires-Dist: black>=23.0.0; extra == 'dev'
Requires-Dist: mypy>=1.0.0; extra == 'dev'
Requires-Dist: pytest-cov>=3.0.0; extra == 'dev'
Requires-Dist: pytest-mock>=3.0.0; extra == 'dev'
Requires-Dist: pytest>=7.0.0; extra == 'dev'
Requires-Dist: ruff>=0.1.0; extra == 'dev'
Provides-Extra: test
Requires-Dist: pytest-cov>=3.0.0; extra == 'test'
Requires-Dist: pytest-mock>=3.0.0; extra == 'test'
Requires-Dist: pytest>=7.0.0; extra == 'test'
